agentu/__init__.py
agentu/agent.py
agentu/cache.py
agentu/cli.py
agentu/eval.py
agentu/mcp_config.py
agentu/mcp_tool.py
agentu/mcp_transport.py
agentu/memory.py
agentu/memory_storage.py
agentu/observe.py
agentu/ralph.py
agentu/search.py
agentu/serve.py
agentu/session.py
agentu/skill.py
agentu/tools.py
agentu/utils.py
agentu/workflow.py
agentu/static/dashboard.html
agentu-1.8.3.dist-info/licenses/LICENSE
agentu-1.8.3.dist-info/METADATA
agentu-1.8.3.dist-info/WHEEL
agentu-1.8.3.dist-info/entry_points.txt
agentu-1.8.3.dist-info/top_level.txt
agentu-1.8.3.dist-info/RECORD
