Metadata-Version: 2.4
Name: agentu
Version: 1.8.3
Summary: A flexible Python package for creating AI agents with customizable tools
Author-email: Hemanth HM <hemanth.hm@gmail.com>
License: MIT License
Project-URL: Homepage, https://github.com/hemanth/agentu
Project-URL: Bug Tracker, https://github.com/hemanth/agentu/issues
Keywords: ai,agents,openai,llm,tools,cli
Classifier: Development Status :: 3 - Alpha
Classifier: Intended Audience :: Developers
Classifier: License :: OSI Approved :: MIT License
Classifier: Programming Language :: Python :: 3
Classifier: Programming Language :: Python :: 3.7
Classifier: Programming Language :: Python :: 3.8
Classifier: Programming Language :: Python :: 3.9
Classifier: Programming Language :: Python :: 3.10
Requires-Python: >=3.9
License-File: LICENSE
Requires-Dist: requests>=2.25.1
Requires-Dist: aiohttp>=3.8.0
Requires-Dist: duckduckgo-search>=4.1.1
Requires-Dist: fastapi>=0.100.0
Requires-Dist: uvicorn>=0.23.0
Requires-Dist: pydantic>=2.0.0
Dynamic: license-file
